emp_app/__init__.py
emp_app/main.py
emp_app-0.5.0.dist-info/METADATA
emp_app-0.5.0.dist-info/WHEEL
emp_app-0.5.0.dist-info/RECORD
