Metadata-Version: 2.1
Name: emp-app
Version: 0.5.0
Summary: 
Author: Rohith Surya Podugu
Author-email: prsurya1020@gmail.com
Requires-Python: >=3.12,<4.0
Classifier: Programming Language :: Python :: 3
Classifier: Programming Language :: Python :: 3.12
Requires-Dist: flask (>=3.0.3,<4.0.0)
Requires-Dist: pre-commit (>=3.7.1,<4.0.0)
Requires-Dist: pytest (>=8.2.2,<9.0.0)
Requires-Dist: requests (>=2.32.3,<3.0.0)
